pvoctopus/LICENSE
pvoctopus/__init__.py
pvoctopus/_factory.py
pvoctopus/_octopus.py
pvoctopus/_util.py
pvoctopus/lib/common/param/octopus_params.pv
pvoctopus/lib/linux/x86_64/libpv_octopus.so
pvoctopus/lib/mac/arm64/libpv_octopus.dylib
pvoctopus/lib/mac/x86_64/libpv_octopus.dylib
pvoctopus/lib/windows/amd64/libpv_octopus.dll
pvoctopus-2.0.2.dist-info/METADATA
pvoctopus-2.0.2.dist-info/WHEEL
pvoctopus-2.0.2.dist-info/top_level.txt
pvoctopus-2.0.2.dist-info/RECORD
